{
  "version": "6",
  "dialect": "sqlite",
  "id": "a079ed18-61af-44bf-b447-6d38af81808a",
  "prevId": "9701fd78-b03d-46d7-b2ee-1fb234d0cc18",
  "tables": {
    "comments": {
      "name": "comments",
      "columns": {
        "id": {
          "name": "id",
          "type": "text",
          "primaryKey": true,
          "notNull": true,
          "autoincrement": false
        },
        "post_id": {
          "name": "post_id",
          "type": "text",
          "primaryKey": false,
          "notNull": true,
          "autoincrement": false
        },
        "author_id": {
          "name": "author_id",
          "type": "text",
          "primaryKey": false,
          "notNull": true,
          "autoincrement": false
        },
        "parent_id": {
          "name": "parent_id",
          "type": "text",
          "primaryKey": false,
          "notNull": false,
          "autoincrement": false
        },
        "content": {
          "name": "content",
          "type": "text",
          "primaryKey": false,
          "notNull": true,
          "autoincrement": false
        },
        "status": {
          "name": "status",
          "type": "text",
          "primaryKey": false,
          "notNull": true,
          "autoincrement": false,
          "default": "'active'"
        },
        "likes_count": {
          "name": "likes_count",
          "type": "integer",
          "primaryKey": false,
          "notNull": false,
          "autoincrement": false,
          "default": 0
        },
        "replies_count": {
          "name": "replies_count",
          "type": "integer",
          "primaryKey": false,
          "notNull": false,
          "autoincrement": false,
          "default": 0
        },
        "reports_count": {
          "name": "reports_count",
          "type": "integer",
          "primaryKey": false,
          "notNull": false,
          "autoincrement": false,
          "default": 0
        },
        "metadata": {
          "name": "metadata",
          "type": "text",
          "primaryKey": false,
          "notNull": false,
          "autoincrement": false
        },
        "created_at": {
          "name": "created_at",
          "type": "integer",
          "primaryKey": false,
          "notNull": false,
          "autoincrement": false,
          "default": "CURRENT_TIMESTAMP"
        },
        "updated_at": {
          "name": "updated_at",
          "type": "integer",
          "primaryKey": false,
          "notNull": false,
          "autoincrement": false,
          "default": "CURRENT_TIMESTAMP"
        }
      },
      "indexes": {},
      "foreignKeys": {
        "comments_post_id_posts_id_fk": {
          "name": "comments_post_id_posts_id_fk",
          "tableFrom": "comments",
          "tableTo": "posts",
          "columnsFrom": [
            "post_id"
          ],
          "columnsTo": [
            "id"
          ],
          "onDelete": "cascade",
          "onUpdate": "no action"
        },
        "comments_author_id_users_id_fk": {
          "name": "comments_author_id_users_id_fk",
          "tableFrom": "comments",
          "tableTo": "users",
          "columnsFrom": [
            "author_id"
          ],
          "columnsTo": [
            "id"
          ],
          "onDelete": "cascade",
          "onUpdate": "no action"
        }
      },
      "compositePrimaryKeys": {},
      "uniqueConstraints": {},
      "checkConstraints": {}
    },
    "likes": {
      "name": "likes",
      "columns": {
        "id": {
          "name": "id",
          "type": "text",
          "primaryKey": true,
          "notNull": true,
          "autoincrement": false
        },
        "user_id": {
          "name": "user_id",
          "type": "text",
          "primaryKey": false,
          "notNull": true,
          "autoincrement": false
        },
        "target_id": {
          "name": "target_id",
          "type": "text",
          "primaryKey": false,
          "notNull": true,
          "autoincrement": false
        },
        "target_type": {
          "name": "target_type",
          "type": "text",
          "primaryKey": false,
          "notNull": true,
          "autoincrement": false
        },
        "reaction": {
          "name": "reaction",
          "type": "text",
          "primaryKey": false,
          "notNull": true,
          "autoincrement": false,
          "default": "'like'"
        },
        "created_at": {
          "name": "created_at",
          "type": "integer",
          "primaryKey": false,
          "notNull": false,
          "autoincrement": false,
          "default": "CURRENT_TIMESTAMP"
        }
      },
      "indexes": {},
      "foreignKeys": {
        "likes_user_id_users_id_fk": {
          "name": "likes_user_id_users_id_fk",
          "tableFrom": "likes",
          "tableTo": "users",
          "columnsFrom": [
            "user_id"
          ],
          "columnsTo": [
            "id"
          ],
          "onDelete": "cascade",
          "onUpdate": "no action"
        }
      },
      "compositePrimaryKeys": {},
      "uniqueConstraints": {},
      "checkConstraints": {}
    },
    "post_shares": {
      "name": "post_shares",
      "columns": {
        "id": {
          "name": "id",
          "type": "text",
          "primaryKey": true,
          "notNull": true,
          "autoincrement": false
        },
        "post_id": {
          "name": "post_id",
          "type": "text",
          "primaryKey": false,
          "notNull": true,
          "autoincrement": false
        },
        "user_id": {
          "name": "user_id",
          "type": "text",
          "primaryKey": false,
          "notNull": true,
          "autoincrement": false
        },
        "share_type": {
          "name": "share_type",
          "type": "text",
          "primaryKey": false,
          "notNull": true,
          "autoincrement": false
        },
        "shared_at": {
          "name": "shared_at",
          "type": "integer",
          "primaryKey": false,
          "notNull": false,
          "autoincrement": false,
          "default": "CURRENT_TIMESTAMP"
        }
      },
      "indexes": {},
      "foreignKeys": {
        "post_shares_post_id_posts_id_fk": {
          "name": "post_shares_post_id_posts_id_fk",
          "tableFrom": "post_shares",
          "tableTo": "posts",
          "columnsFrom": [
            "post_id"
          ],
          "columnsTo": [
            "id"
          ],
          "onDelete": "cascade",
          "onUpdate": "no action"
        },
        "post_shares_user_id_users_id_fk": {
          "name": "post_shares_user_id_users_id_fk",
          "tableFrom": "post_shares",
          "tableTo": "users",
          "columnsFrom": [
            "user_id"
          ],
          "columnsTo": [
            "id"
          ],
          "onDelete": "cascade",
          "onUpdate": "no action"
        }
      },
      "compositePrimaryKeys": {},
      "uniqueConstraints": {},
      "checkConstraints": {}
    },
    "post_views": {
      "name": "post_views",
      "columns": {
        "id": {
          "name": "id",
          "type": "text",
          "primaryKey": true,
          "notNull": true,
          "autoincrement": false
        },
        "post_id": {
          "name": "post_id",
          "type": "text",
          "primaryKey": false,
          "notNull": true,
          "autoincrement": false
        },
        "user_id": {
          "name": "user_id",
          "type": "text",
          "primaryKey": false,
          "notNull": false,
          "autoincrement": false
        },
        "ip_address": {
          "name": "ip_address",
          "type": "text",
          "primaryKey": false,
          "notNull": false,
          "autoincrement": false
        },
        "user_agent": {
          "name": "user_agent",
          "type": "text",
          "primaryKey": false,
          "notNull": false,
          "autoincrement": false
        },
        "viewed_at": {
          "name": "viewed_at",
          "type": "integer",
          "primaryKey": false,
          "notNull": false,
          "autoincrement": false,
          "default": "CURRENT_TIMESTAMP"
        }
      },
      "indexes": {},
      "foreignKeys": {
        "post_views_post_id_posts_id_fk": {
          "name": "post_views_post_id_posts_id_fk",
          "tableFrom": "post_views",
          "tableTo": "posts",
          "columnsFrom": [
            "post_id"
          ],
          "columnsTo": [
            "id"
          ],
          "onDelete": "cascade",
          "onUpdate": "no action"
        },
        "post_views_user_id_users_id_fk": {
          "name": "post_views_user_id_users_id_fk",
          "tableFrom": "post_views",
          "tableTo": "users",
          "columnsFrom": [
            "user_id"
          ],
          "columnsTo": [
            "id"
          ],
          "onDelete": "cascade",
          "onUpdate": "no action"
        }
      },
      "compositePrimaryKeys": {},
      "uniqueConstraints": {},
      "checkConstraints": {}
    },
    "posts": {
      "name": "posts",
      "columns": {
        "id": {
          "name": "id",
          "type": "text",
          "primaryKey": true,
          "notNull": true,
          "autoincrement": false
        },
        "author_id": {
          "name": "author_id",
          "type": "text",
          "primaryKey": false,
          "notNull": true,
          "autoincrement": false
        },
        "type": {
          "name": "type",
          "type": "text",
          "primaryKey": false,
          "notNull": true,
          "autoincrement": false,
          "default": "'text'"
        },
        "privacy": {
          "name": "privacy",
          "type": "text",
          "primaryKey": false,
          "notNull": true,
          "autoincrement": false,
          "default": "'public'"
        },
        "content": {
          "name": "content",
          "type": "text",
          "primaryKey": false,
          "notNull": true,
          "autoincrement": false
        },
        "likes_count": {
          "name": "likes_count",
          "type": "integer",
          "primaryKey": false,
          "notNull": false,
          "autoincrement": false,
          "default": 0
        },
        "comments_count": {
          "name": "comments_count",
          "type": "integer",
          "primaryKey": false,
          "notNull": false,
          "autoincrement": false,
          "default": 0
        },
        "shares_count": {
          "name": "shares_count",
          "type": "integer",
          "primaryKey": false,
          "notNull": false,
          "autoincrement": false,
          "default": 0
        },
        "views_count": {
          "name": "views_count",
          "type": "integer",
          "primaryKey": false,
          "notNull": false,
          "autoincrement": false,
          "default": 0
        },
        "engagement_rate": {
          "name": "engagement_rate",
          "type": "real",
          "primaryKey": false,
          "notNull": false,
          "autoincrement": false,
          "default": 0
        },
        "metadata": {
          "name": "metadata",
          "type": "text",
          "primaryKey": false,
          "notNull": false,
          "autoincrement": false
        },
        "created_at": {
          "name": "created_at",
          "type": "integer",
          "primaryKey": false,
          "notNull": false,
          "autoincrement": false,
          "default": "CURRENT_TIMESTAMP"
        },
        "updated_at": {
          "name": "updated_at",
          "type": "integer",
          "primaryKey": false,
          "notNull": false,
          "autoincrement": false,
          "default": "CURRENT_TIMESTAMP"
        },
        "published_at": {
          "name": "published_at",
          "type": "integer",
          "primaryKey": false,
          "notNull": false,
          "autoincrement": false
        },
        "scheduled_for": {
          "name": "scheduled_for",
          "type": "integer",
          "primaryKey": false,
          "notNull": false,
          "autoincrement": false
        }
      },
      "indexes": {},
      "foreignKeys": {
        "posts_author_id_users_id_fk": {
          "name": "posts_author_id_users_id_fk",
          "tableFrom": "posts",
          "tableTo": "users",
          "columnsFrom": [
            "author_id"
          ],
          "columnsTo": [
            "id"
          ],
          "onDelete": "cascade",
          "onUpdate": "no action"
        }
      },
      "compositePrimaryKeys": {},
      "uniqueConstraints": {},
      "checkConstraints": {}
    },
    "user_activity_log": {
      "name": "user_activity_log",
      "columns": {
        "id": {
          "name": "id",
          "type": "text",
          "primaryKey": true,
          "notNull": true,
          "autoincrement": false
        },
        "user_id": {
          "name": "user_id",
          "type": "text",
          "primaryKey": false,
          "notNull": true,
          "autoincrement": false
        },
        "activity": {
          "name": "activity",
          "type": "text",
          "primaryKey": false,
          "notNull": true,
          "autoincrement": false
        },
        "metadata": {
          "name": "metadata",
          "type": "text",
          "primaryKey": false,
          "notNull": false,
          "autoincrement": false
        },
        "ip_address": {
          "name": "ip_address",
          "type": "text",
          "primaryKey": false,
          "notNull": false,
          "autoincrement": false
        },
        "user_agent": {
          "name": "user_agent",
          "type": "text",
          "primaryKey": false,
          "notNull": false,
          "autoincrement": false
        },
        "created_at": {
          "name": "created_at",
          "type": "integer",
          "primaryKey": false,
          "notNull": false,
          "autoincrement": false,
          "default": "CURRENT_TIMESTAMP"
        }
      },
      "indexes": {},
      "foreignKeys": {
        "user_activity_log_user_id_users_id_fk": {
          "name": "user_activity_log_user_id_users_id_fk",
          "tableFrom": "user_activity_log",
          "tableTo": "users",
          "columnsFrom": [
            "user_id"
          ],
          "columnsTo": [
            "id"
          ],
          "onDelete": "cascade",
          "onUpdate": "no action"
        }
      },
      "compositePrimaryKeys": {},
      "uniqueConstraints": {},
      "checkConstraints": {}
    },
    "user_permissions": {
      "name": "user_permissions",
      "columns": {
        "id": {
          "name": "id",
          "type": "text",
          "primaryKey": true,
          "notNull": true,
          "autoincrement": false
        },
        "user_id": {
          "name": "user_id",
          "type": "text",
          "primaryKey": false,
          "notNull": true,
          "autoincrement": false
        },
        "permission": {
          "name": "permission",
          "type": "text",
          "primaryKey": false,
          "notNull": true,
          "autoincrement": false
        },
        "granted_at": {
          "name": "granted_at",
          "type": "integer",
          "primaryKey": false,
          "notNull": false,
          "autoincrement": false,
          "default": "CURRENT_TIMESTAMP"
        },
        "granted_by": {
          "name": "granted_by",
          "type": "text",
          "primaryKey": false,
          "notNull": false,
          "autoincrement": false
        },
        "expires_at": {
          "name": "expires_at",
          "type": "integer",
          "primaryKey": false,
          "notNull": false,
          "autoincrement": false
        }
      },
      "indexes": {},
      "foreignKeys": {
        "user_permissions_user_id_users_id_fk": {
          "name": "user_permissions_user_id_users_id_fk",
          "tableFrom": "user_permissions",
          "tableTo": "users",
          "columnsFrom": [
            "user_id"
          ],
          "columnsTo": [
            "id"
          ],
          "onDelete": "cascade",
          "onUpdate": "no action"
        },
        "user_permissions_granted_by_users_id_fk": {
          "name": "user_permissions_granted_by_users_id_fk",
          "tableFrom": "user_permissions",
          "tableTo": "users",
          "columnsFrom": [
            "granted_by"
          ],
          "columnsTo": [
            "id"
          ],
          "onDelete": "no action",
          "onUpdate": "no action"
        }
      },
      "compositePrimaryKeys": {},
      "uniqueConstraints": {},
      "checkConstraints": {}
    },
    "user_sessions": {
      "name": "user_sessions",
      "columns": {
        "id": {
          "name": "id",
          "type": "text",
          "primaryKey": true,
          "notNull": true,
          "autoincrement": false
        },
        "user_id": {
          "name": "user_id",
          "type": "text",
          "primaryKey": false,
          "notNull": true,
          "autoincrement": false
        },
        "session_token": {
          "name": "session_token",
          "type": "text",
          "primaryKey": false,
          "notNull": true,
          "autoincrement": false
        },
        "expires_at": {
          "name": "expires_at",
          "type": "integer",
          "primaryKey": false,
          "notNull": true,
          "autoincrement": false
        },
        "created_at": {
          "name": "created_at",
          "type": "integer",
          "primaryKey": false,
          "notNull": false,
          "autoincrement": false,
          "default": "CURRENT_TIMESTAMP"
        },
        "last_activity_at": {
          "name": "last_activity_at",
          "type": "integer",
          "primaryKey": false,
          "notNull": false,
          "autoincrement": false,
          "default": "CURRENT_TIMESTAMP"
        }
      },
      "indexes": {
        "user_sessions_session_token_unique": {
          "name": "user_sessions_session_token_unique",
          "columns": [
            "session_token"
          ],
          "isUnique": true
        }
      },
      "foreignKeys": {
        "user_sessions_user_id_users_id_fk": {
          "name": "user_sessions_user_id_users_id_fk",
          "tableFrom": "user_sessions",
          "tableTo": "users",
          "columnsFrom": [
            "user_id"
          ],
          "columnsTo": [
            "id"
          ],
          "onDelete": "cascade",
          "onUpdate": "no action"
        }
      },
      "compositePrimaryKeys": {},
      "uniqueConstraints": {},
      "checkConstraints": {}
    },
    "user_settings": {
      "name": "user_settings",
      "columns": {
        "id": {
          "name": "id",
          "type": "text",
          "primaryKey": true,
          "notNull": true,
          "autoincrement": false
        },
        "user_id": {
          "name": "user_id",
          "type": "text",
          "primaryKey": false,
          "notNull": true,
          "autoincrement": false
        },
        "setting_key": {
          "name": "setting_key",
          "type": "text",
          "primaryKey": false,
          "notNull": true,
          "autoincrement": false
        },
        "setting_value": {
          "name": "setting_value",
          "type": "text",
          "primaryKey": false,
          "notNull": false,
          "autoincrement": false
        },
        "created_at": {
          "name": "created_at",
          "type": "integer",
          "primaryKey": false,
          "notNull": false,
          "autoincrement": false,
          "default": "CURRENT_TIMESTAMP"
        },
        "updated_at": {
          "name": "updated_at",
          "type": "integer",
          "primaryKey": false,
          "notNull": false,
          "autoincrement": false,
          "default": "CURRENT_TIMESTAMP"
        }
      },
      "indexes": {},
      "foreignKeys": {
        "user_settings_user_id_users_id_fk": {
          "name": "user_settings_user_id_users_id_fk",
          "tableFrom": "user_settings",
          "tableTo": "users",
          "columnsFrom": [
            "user_id"
          ],
          "columnsTo": [
            "id"
          ],
          "onDelete": "cascade",
          "onUpdate": "no action"
        }
      },
      "compositePrimaryKeys": {},
      "uniqueConstraints": {},
      "checkConstraints": {}
    },
    "users": {
      "name": "users",
      "columns": {
        "id": {
          "name": "id",
          "type": "text",
          "primaryKey": true,
          "notNull": true,
          "autoincrement": false
        },
        "email": {
          "name": "email",
          "type": "text",
          "primaryKey": false,
          "notNull": true,
          "autoincrement": false
        },
        "username": {
          "name": "username",
          "type": "text",
          "primaryKey": false,
          "notNull": false,
          "autoincrement": false
        },
        "role": {
          "name": "role",
          "type": "text",
          "primaryKey": false,
          "notNull": true,
          "autoincrement": false,
          "default": "'user'"
        },
        "status": {
          "name": "status",
          "type": "text",
          "primaryKey": false,
          "notNull": true,
          "autoincrement": false,
          "default": "'active'"
        },
        "display_name": {
          "name": "display_name",
          "type": "text",
          "primaryKey": false,
          "notNull": false,
          "autoincrement": false
        },
        "bio": {
          "name": "bio",
          "type": "text",
          "primaryKey": false,
          "notNull": false,
          "autoincrement": false
        },
        "avatar": {
          "name": "avatar",
          "type": "text",
          "primaryKey": false,
          "notNull": false,
          "autoincrement": false
        },
        "cover_image": {
          "name": "cover_image",
          "type": "text",
          "primaryKey": false,
          "notNull": false,
          "autoincrement": false
        },
        "location": {
          "name": "location",
          "type": "text",
          "primaryKey": false,
          "notNull": false,
          "autoincrement": false
        },
        "website": {
          "name": "website",
          "type": "text",
          "primaryKey": false,
          "notNull": false,
          "autoincrement": false
        },
        "social_links": {
          "name": "social_links",
          "type": "text",
          "primaryKey": false,
          "notNull": false,
          "autoincrement": false
        },
        "preferences": {
          "name": "preferences",
          "type": "text",
          "primaryKey": false,
          "notNull": false,
          "autoincrement": false
        },
        "posts_count": {
          "name": "posts_count",
          "type": "integer",
          "primaryKey": false,
          "notNull": false,
          "autoincrement": false,
          "default": 0
        },
        "followers_count": {
          "name": "followers_count",
          "type": "integer",
          "primaryKey": false,
          "notNull": false,
          "autoincrement": false,
          "default": 0
        },
        "following_count": {
          "name": "following_count",
          "type": "integer",
          "primaryKey": false,
          "notNull": false,
          "autoincrement": false,
          "default": 0
        },
        "likes_received": {
          "name": "likes_received",
          "type": "integer",
          "primaryKey": false,
          "notNull": false,
          "autoincrement": false,
          "default": 0
        },
        "comments_count": {
          "name": "comments_count",
          "type": "integer",
          "primaryKey": false,
          "notNull": false,
          "autoincrement": false,
          "default": 0
        },
        "products_count": {
          "name": "products_count",
          "type": "integer",
          "primaryKey": false,
          "notNull": false,
          "autoincrement": false,
          "default": 0
        },
        "orders_count": {
          "name": "orders_count",
          "type": "integer",
          "primaryKey": false,
          "notNull": false,
          "autoincrement": false,
          "default": 0
        },
        "total_earnings": {
          "name": "total_earnings",
          "type": "real",
          "primaryKey": false,
          "notNull": false,
          "autoincrement": false,
          "default": 0
        },
        "last_active_at": {
          "name": "last_active_at",
          "type": "integer",
          "primaryKey": false,
          "notNull": false,
          "autoincrement": false
        },
        "email_verified": {
          "name": "email_verified",
          "type": "integer",
          "primaryKey": false,
          "notNull": false,
          "autoincrement": false,
          "default": false
        },
        "phone_verified": {
          "name": "phone_verified",
          "type": "integer",
          "primaryKey": false,
          "notNull": false,
          "autoincrement": false,
          "default": false
        },
        "identity_verified": {
          "name": "identity_verified",
          "type": "integer",
          "primaryKey": false,
          "notNull": false,
          "autoincrement": false,
          "default": false
        },
        "kyc_completed": {
          "name": "kyc_completed",
          "type": "integer",
          "primaryKey": false,
          "notNull": false,
          "autoincrement": false,
          "default": false
        },
        "verification_documents": {
          "name": "verification_documents",
          "type": "text",
          "primaryKey": false,
          "notNull": false,
          "autoincrement": false
        },
        "verification_status": {
          "name": "verification_status",
          "type": "text",
          "primaryKey": false,
          "notNull": false,
          "autoincrement": false,
          "default": "'pending'"
        },
        "verification_date": {
          "name": "verification_date",
          "type": "integer",
          "primaryKey": false,
          "notNull": false,
          "autoincrement": false
        },
        "face_verified": {
          "name": "face_verified",
          "type": "integer",
          "primaryKey": false,
          "notNull": false,
          "autoincrement": false,
          "default": false
        },
        "face_id": {
          "name": "face_id",
          "type": "text",
          "primaryKey": false,
          "notNull": false,
          "autoincrement": false
        },
        "face_enrollment_date": {
          "name": "face_enrollment_date",
          "type": "integer",
          "primaryKey": false,
          "notNull": false,
          "autoincrement": false
        },
        "face_verification_enabled": {
          "name": "face_verification_enabled",
          "type": "integer",
          "primaryKey": false,
          "notNull": false,
          "autoincrement": false,
          "default": false
        },
        "created_at": {
          "name": "created_at",
          "type": "integer",
          "primaryKey": false,
          "notNull": false,
          "autoincrement": false,
          "default": "CURRENT_TIMESTAMP"
        },
        "updated_at": {
          "name": "updated_at",
          "type": "integer",
          "primaryKey": false,
          "notNull": false,
          "autoincrement": false,
          "default": "CURRENT_TIMESTAMP"
        },
        "last_login_at": {
          "name": "last_login_at",
          "type": "integer",
          "primaryKey": false,
          "notNull": false,
          "autoincrement": false
        }
      },
      "indexes": {
        "users_email_unique": {
          "name": "users_email_unique",
          "columns": [
            "email"
          ],
          "isUnique": true
        },
        "users_username_unique": {
          "name": "users_username_unique",
          "columns": [
            "username"
          ],
          "isUnique": true
        }
      },
      "foreignKeys": {},
      "compositePrimaryKeys": {},
      "uniqueConstraints": {},
      "checkConstraints": {}
    }
  },
  "views": {},
  "enums": {},
  "_meta": {
    "schemas": {},
    "tables": {},
    "columns": {}
  },
  "internal": {
    "indexes": {}
  }
}